air/__init__.py
air/base_handler.py
air/plugins.py
air_df-0.1.3.dist-info/LICENSE
air_df-0.1.3.dist-info/METADATA
air_df-0.1.3.dist-info/WHEEL
air_df-0.1.3.dist-info/top_level.txt
air_df-0.1.3.dist-info/RECORD
