Metadata-Version: 2.1
Name: air-df
Version: 0.1.3
Summary: 常用插件
Home-page: https://github.com/Air-df
Author: Damon
Author-email: 527439841@qq.com
License: UNKNOWN
Platform: UNKNOWN
Classifier: Programming Language :: Python :: 3.9
Classifier: License :: OSI Approved :: MIT License
Classifier: Operating System :: OS Independent
Requires-Dist: redis (~=4.0.2)
Requires-Dist: pymongo (~=4.0)
Requires-Dist: xlrd (~=1.2.0)
Requires-Dist: captcha (~=0.3)
Requires-Dist: Faker (~=9.9.0)
Requires-Dist: SQLAlchemy (~=1.4.21)
Requires-Dist: XlsxWriter (~=3.0.2)
Requires-Dist: tornado (~=6.1)
Requires-Dist: setuptools (~=49.2.1)
